pdm_foo-0.1.0.dist-info/METADATA
pdm_foo-0.1.0.dist-info/WHEEL
pdm_foo-0.1.0.dist-info/entry_points.txt
pdm_foo-0.1.0.dist-info/licenses/LICENSE
pdm_foo/__init__.py
pdm_foo-0.1.0.dist-info/RECORD
