Metadata-Version: 2.1
Name: pdm-foo
Version: 0.1.0
Summary: Default template for PDM package
Author-Email: galenseilis <galen.seilis@seilis.ca>
License: GNU GPL 3.0
Requires-Python: >=3.12
